{
    "2017-02-25": {
        "asn": {
            "allocated": 7595,
            "assigned": 0,
            "available": 443,
            "given": 14973,
            "reserved": 0
        },
        "ipv4": {
            "allocated": 25674,
            "assigned": 11169,
            "available": 16,
            "hosts": 880634880,
            "reserved": 892
        },
        "ipv6": {
            "allocated": 4601,
            "assigned": 1611,
            "available": 39742,
            "reserved": 471
        }
    },
    "2017-02-26": {
        "asn": {
            "allocated": 7595,
            "assigned": 0,
            "available": 443,
            "given": 14973,
            "reserved": 0
        },
        "ipv4": {
            "allocated": 25674,
            "assigned": 11169,
            "available": 16,
            "hosts": 880634880,
            "reserved": 892
        },
        "ipv6": {
            "allocated": 4601,
            "assigned": 1612,
            "available": 39749,
            "reserved": 471
        }
    },
    "2017-02-27": {
        "asn": {
            "allocated": 7595,
            "assigned": 0,
            "available": 443,
            "given": 14973,
            "reserved": 0
        },
        "ipv4": {
            "allocated": 25678,
            "assigned": 11169,
            "available": 16,
            "hosts": 880634880,
            "reserved": 892
        },
        "ipv6": {
            "allocated": 4601,
            "assigned": 1612,
            "available": 39749,
            "reserved": 471
        }
    },
    "2017-02-28": {
        "asn": {
            "allocated": 7599,
            "assigned": 0,
            "available": 443,
            "given": 14973,
            "reserved": 0
        },
        "ipv4": {
            "allocated": 25678,
            "assigned": 11170,
            "available": 15,
            "hosts": 880634880,
            "reserved": 892
        },
        "ipv6": {
            "allocated": 4604,
            "assigned": 1612,
            "available": 39764,
            "reserved": 471
        }
    },
    "2017-03-01": {
        "asn": {
            "allocated": 7605,
            "assigned": 0,
            "available": 443,
            "given": 14973,
            "reserved": 0
        },
        "ipv4": {
            "allocated": 25682,
            "assigned": 11170,
            "available": 14,
            "hosts": 880632832,
            "reserved": 892
        },
        "ipv6": {
            "allocated": 4606,
            "assigned": 1612,
            "available": 39774,
            "reserved": 471
        }
    },
    "2017-03-02": {
        "asn": {
            "allocated": 7609,
            "assigned": 0,
            "available": 443,
            "given": 14973,
            "reserved": 0
        },
        "ipv4": {
            "allocated": 25686,
            "assigned": 11170,
            "available": 16,
            "hosts": 880632832,
            "reserved": 891
        },
        "ipv6": {
            "allocated": 4610,
            "assigned": 1613,
            "available": 39801,
            "reserved": 471
        }
    },
    "2017-03-03": {
        "asn": {
            "allocated": 7614,
            "assigned": 0,
            "available": 442,
            "given": 14973,
            "reserved": 0
        },
        "ipv4": {
            "allocated": 25704,
            "assigned": 11173,
            "available": 22,
            "hosts": 880641024,
            "reserved": 890
        },
        "ipv6": {
            "allocated": 4630,
            "assigned": 1614,
            "available": 39903,
            "reserved": 470
        }
    },
    "2017-03-04": {
        "asn": {
            "allocated": 7613,
            "assigned": 0,
            "available": 443,
            "given": 14973,
            "reserved": 0
        },
        "ipv4": {
            "allocated": 25707,
            "assigned": 11176,
            "available": 23,
            "hosts": 880641024,
            "reserved": 891
        },
        "ipv6": {
            "allocated": 4632,
            "assigned": 1617,
            "available": 39934,
            "reserved": 470
        }
    },
    "2017-03-05": {
        "asn": {
            "allocated": 7613,
            "assigned": 0,
            "available": 443,
            "given": 14973,
            "reserved": 0
        },
        "ipv4": {
            "allocated": 25707,
            "assigned": 11177,
            "available": 23,
            "hosts": 880641024,
            "reserved": 891
        },
        "ipv6": {
            "allocated": 4632,
            "assigned": 1617,
            "available": 39934,
            "reserved": 470
        }
    },
    "2017-03-06": {
        "asn": {
            "allocated": 7613,
            "assigned": 0,
            "available": 443,
            "given": 14973,
            "reserved": 0
        },
        "ipv4": {
            "allocated": 25707,
            "assigned": 11177,
            "available": 23,
            "hosts": 880641024,
            "reserved": 891
        },
        "ipv6": {
            "allocated": 4632,
            "assigned": 1617,
            "available": 39934,
            "reserved": 470
        }
    },
    "2017-03-07": {
        "asn": {
            "allocated": 7611,
            "assigned": 0,
            "available": 446,
            "given": 14973,
            "reserved": 0
        },
        "ipv4": {
            "allocated": 25709,
            "assigned": 11182,
            "available": 22,
            "hosts": 880641024,
            "reserved": 893
        },
        "ipv6": {
            "allocated": 4633,
            "assigned": 1618,
            "available": 39960,
            "reserved": 472
        }
    },
    "2017-03-08": {
        "asn": {
            "allocated": 7614,
            "assigned": 0,
            "available": 446,
            "given": 14973,
            "reserved": 0
        },
        "ipv4": {
            "allocated": 25716,
            "assigned": 11189,
            "available": 21,
            "hosts": 880641024,
            "reserved": 893
        },
        "ipv6": {
            "allocated": 4636,
            "assigned": 1619,
            "available": 39982,
            "reserved": 472
        }
    },
    "2017-03-09": {
        "asn": {
            "allocated": 7617,
            "assigned": 0,
            "available": 446,
            "given": 14973,
            "reserved": 0
        },
        "ipv4": {
            "allocated": 25723,
            "assigned": 11193,
            "available": 22,
            "hosts": 880641024,
            "reserved": 894
        },
        "ipv6": {
            "allocated": 4640,
            "assigned": 1623,
            "available": 40029,
            "reserved": 473
        }
    },
    "2017-03-10": {
        "asn": {
            "allocated": 7617,
            "assigned": 0,
            "available": 447,
            "given": 14973,
            "reserved": 0
        },
        "ipv4": {
            "allocated": 25730,
            "assigned": 11199,
            "available": 20,
            "hosts": 880645120,
            "reserved": 894
        },
        "ipv6": {
            "allocated": 4641,
            "assigned": 1624,
            "available": 40046,
            "reserved": 474
        }
    },
    "2017-03-11": {
        "asn": {
            "allocated": 7619,
            "assigned": 0,
            "available": 449,
            "given": 14973,
            "reserved": 0
        },
        "ipv4": {
            "allocated": 25737,
            "assigned": 11205,
            "available": 20,
            "hosts": 880645120,
            "reserved": 894
        },
        "ipv6": {
            "allocated": 4646,
            "assigned": 1627,
            "available": 40106,
            "reserved": 476
        }
    },
    "2017-03-12": {
        "asn": {
            "allocated": 7619,
            "assigned": 0,
            "available": 449,
            "given": 14973,
            "reserved": 0
        },
        "ipv4": {
            "allocated": 25737,
            "assigned": 11205,
            "available": 20,
            "hosts": 880645120,
            "reserved": 894
        },
        "ipv6": {
            "allocated": 4646,
            "assigned": 1627,
            "available": 40106,
            "reserved": 476
        }
    },
    "2017-03-13": {
        "asn": {
            "allocated": 7619,
            "assigned": 0,
            "available": 449,
            "given": 14973,
            "reserved": 0
        },
        "ipv4": {
            "allocated": 25737,
            "assigned": 11205,
            "available": 20,
            "hosts": 880645120,
            "reserved": 894
        },
        "ipv6": {
            "allocated": 4646,
            "assigned": 1627,
            "available": 40106,
            "reserved": 476
        }
    },
    "2017-03-14": {
        "asn": {
            "allocated": 7621,
            "assigned": 0,
            "available": 449,
            "given": 14973,
            "reserved": 0
        },
        "ipv4": {
            "allocated": 25742,
            "assigned": 11207,
            "available": 21,
            "hosts": 880645120,
            "reserved": 894
        },
        "ipv6": {
            "allocated": 4649,
            "assigned": 1628,
            "available": 40122,
            "reserved": 476
        }
    },
    "2017-03-15": {
        "asn": {
            "allocated": 7617,
            "assigned": 0,
            "available": 453,
            "given": 14972,
            "reserved": 0
        },
        "ipv4": {
            "allocated": 25746,
            "assigned": 11206,
            "available": 20,
            "hosts": 880649216,
            "reserved": 902
        },
        "ipv6": {
            "allocated": 4651,
            "assigned": 1627,
            "available": 40132,
            "reserved": 477
        }
    },
    "2017-03-16": {
        "asn": {
            "allocated": 7622,
            "assigned": 0,
            "available": 453,
            "given": 14973,
            "reserved": 0
        },
        "ipv4": {
            "allocated": 25750,
            "assigned": 11206,
            "available": 27,
            "hosts": 880649216,
            "reserved": 902
        },
        "ipv6": {
            "allocated": 4652,
            "assigned": 1627,
            "available": 40137,
            "reserved": 477
        }
    },
    "2017-03-17": {
        "asn": {
            "allocated": 7624,
            "assigned": 0,
            "available": 454,
            "given": 14973,
            "reserved": 0
        },
        "ipv4": {
            "allocated": 25763,
            "assigned": 11206,
            "available": 24,
            "hosts": 880649216,
            "reserved": 902
        },
        "ipv6": {
            "allocated": 4657,
            "assigned": 1627,
            "available": 40162,
            "reserved": 477
        }
    },
    "2017-03-18": {
        "asn": {
            "allocated": 7625,
            "assigned": 0,
            "available": 454,
            "given": 14973,
            "reserved": 0
        },
        "ipv4": {
            "allocated": 25765,
            "assigned": 11211,
            "available": 23,
            "hosts": 880649216,
            "reserved": 902
        },
        "ipv6": {
            "allocated": 4660,
            "assigned": 1628,
            "available": 40184,
            "reserved": 477
        }
    },
    "2017-03-19": {
        "asn": {
            "allocated": 7625,
            "assigned": 0,
            "available": 454,
            "given": 14973,
            "reserved": 0
        },
        "ipv4": {
            "allocated": 25765,
            "assigned": 11211,
            "available": 23,
            "hosts": 880649216,
            "reserved": 902
        },
        "ipv6": {
            "allocated": 4660,
            "assigned": 1629,
            "available": 40191,
            "reserved": 477
        }
    },
    "2017-03-20": {
        "asn": {
            "allocated": 7625,
            "assigned": 0,
            "available": 454,
            "given": 14973,
            "reserved": 0
        },
        "ipv4": {
            "allocated": 25767,
            "assigned": 11211,
            "available": 25,
            "hosts": 880649216,
            "reserved": 902
        },
        "ipv6": {
            "allocated": 4660,
            "assigned": 1629,
            "available": 40191,
            "reserved": 477
        }
    },
    "2017-03-21": {
        "asn": {
            "allocated": 7628,
            "assigned": 0,
            "available": 454,
            "given": 14973,
            "reserved": 0
        },
        "ipv4": {
            "allocated": 25772,
            "assigned": 11213,
            "available": 23,
            "hosts": 880658432,
            "reserved": 903
        },
        "ipv6": {
            "allocated": 4661,
            "assigned": 1629,
            "available": 40196,
            "reserved": 477
        }
    },
    "2017-03-22": {
        "asn": {
            "allocated": 7630,
            "assigned": 0,
            "available": 455,
            "given": 14972,
            "reserved": 0
        },
        "ipv4": {
            "allocated": 25778,
            "assigned": 11217,
            "available": 24,
            "hosts": 880658432,
            "reserved": 905
        },
        "ipv6": {
            "allocated": 4667,
            "assigned": 1630,
            "available": 40238,
            "reserved": 478
        }
    }
}